odoo/addons/ssi_tag_mixin/README.rst
odoo/addons/ssi_tag_mixin/__init__.py
odoo/addons/ssi_tag_mixin/__manifest__.py
odoo/addons/ssi_tag_mixin/menu.xml
odoo/addons/ssi_tag_mixin/models/__init__.py
odoo/addons/ssi_tag_mixin/models/global_tag.py
odoo/addons/ssi_tag_mixin/models/global_tag_category.py
odoo/addons/ssi_tag_mixin/models/ir_model.py
odoo/addons/ssi_tag_mixin/models/mixin_tag.py
odoo/addons/ssi_tag_mixin/security/ir.model.access.csv
odoo/addons/ssi_tag_mixin/static/description/icon.png
odoo/addons/ssi_tag_mixin/views/global_tag_category_views.xml
odoo/addons/ssi_tag_mixin/views/global_tag_views.xml
odoo/addons/ssi_tag_mixin/views/ir_model_views.xml
odoo14_addon_ssi_tag_mixin-14.0.1.0.1.dev2.dist-info/METADATA
odoo14_addon_ssi_tag_mixin-14.0.1.0.1.dev2.dist-info/WHEEL
odoo14_addon_ssi_tag_mixin-14.0.1.0.1.dev2.dist-info/top_level.txt
odoo14_addon_ssi_tag_mixin-14.0.1.0.1.dev2.dist-info/RECORD
